shift/shift.v
module shiftStage #(parameter N = 1) (
    input  [15:0] IN,
    input         SFTOUT1,   // carry chain in
    input         SFTIN,     // incoming ALU flagC, broadcast
    input  [1:0]  SHIFTOPC,
    input         EN,
    output [15:0] OUT,
    output        SFTOUT2
);
    wire fillBit = (SHIFTOPC == 2'b10) ? IN[15] :   // ASR: sign bit
                   (SHIFTOPC == 2'b11) ? SFTIN  :   // XSR: incoming flagC
                   1'b0;                             // LSL/LSR: zero

    wire [15:0] leftShifted  = {IN[15-N:0], {N{1'b0}}};
    wire [15:0] rightShifted = {{N{fillBit}}, IN[15:N]};

    wire [15:0] shiftedVal = (SHIFTOPC == 2'b00) ? leftShifted : rightShifted;
    wire fallenBit         = (SHIFTOPC == 2'b00) ? IN[16-N] : IN[N-1];

    assign OUT     = EN ? shiftedVal : IN;
    assign SFTOUT2 = EN ? fallenBit  : SFTOUT1;
endmodule

module shift(
    input  [15:0] IN,
    input  [3:0]  SCNT,
    input  [1:0]  SHIFTOPC,
    input         SFTIN,
    output [15:0] OUT,
    output        SFTOUT
);
    wire [15:0] out1, out2, out4;
    wire        sf1, sf2, sf4;
    wire [3:0]  effSCNT;

    // XSR always shifts by exactly 1, regardless of what SCNT says
    assign effSCNT = (SHIFTOPC == 2'b11) ? 4'b0001 : SCNT;

    shiftStage #(1) SHIFT1(.IN(IN),   .SFTOUT1(1'b0), .SFTIN(SFTIN), .SHIFTOPC(SHIFTOPC), .EN(effSCNT[0]), .OUT(out1), .SFTOUT2(sf1));
    shiftStage #(2) SHIFT2(.IN(out1), .SFTOUT1(sf1),  .SFTIN(SFTIN), .SHIFTOPC(SHIFTOPC), .EN(effSCNT[1]), .OUT(out2), .SFTOUT2(sf2));
    shiftStage #(4) SHIFT4(.IN(out2), .SFTOUT1(sf2),  .SFTIN(SFTIN), .SHIFTOPC(SHIFTOPC), .EN(effSCNT[2]), .OUT(out4), .SFTOUT2(sf4));
    shiftStage #(8) SHIFT8(.IN(out4), .SFTOUT1(sf4),  .SFTIN(SFTIN), .SHIFTOPC(SHIFTOPC), .EN(effSCNT[3]), .OUT(OUT),  .SFTOUT2(SFTOUT));
endmodule

shift/shift_tb.v
`timescale 1ns/1ps

module shift_tb;
    reg  [15:0] IN;
    reg  [3:0]  SCNT;
    reg  [1:0]  SHIFTOPC;
    reg         SFTIN;
    wire [15:0] OUT;
    wire        SFTOUT;

    shift uut (
        .IN(IN),
        .SCNT(SCNT),
        .SHIFTOPC(SHIFTOPC),
        .SFTIN(SFTIN),
        .OUT(OUT),
        .SFTOUT(SFTOUT)
    );

    initial begin
        $dumpfile("dump_shift.vcd");
        $dumpvars(0, shift_tb);

        $display("         IN          SCNT OPC SFTIN |        OUT       SFTOUT");
        $display("--------------------------------------------------------------------");

        IN = 16'b0000_0000_0000_1011; SCNT = 4'b0000; SHIFTOPC = 2'b00; SFTIN = 1'b0; #10;
        $display("%b  %b  %b   %b  |  %b  %b", IN, SCNT, SHIFTOPC, SFTIN, OUT, SFTOUT);

        IN = 16'b0000_0000_0000_1011; SCNT = 4'b0010; SHIFTOPC = 2'b00; SFTIN = 1'b0; #10;
        $display("%b  %b  %b   %b  |  %b  %b", IN, SCNT, SHIFTOPC, SFTIN, OUT, SFTOUT);

        IN = 16'b1111_1111_1111_1111; SCNT = 4'b1000; SHIFTOPC = 2'b00; SFTIN = 1'b0; #10;
        $display("%b  %b  %b   %b  |  %b  %b", IN, SCNT, SHIFTOPC, SFTIN, OUT, SFTOUT);

        IN = 16'b1000_0000_0000_0000; SCNT = 4'b0001; SHIFTOPC = 2'b01; SFTIN = 1'b0; #10;
        $display("%b  %b  %b   %b  |  %b  %b", IN, SCNT, SHIFTOPC, SFTIN, OUT, SFTOUT);

        IN = 16'b1111_1111_1111_1111; SCNT = 4'b0100; SHIFTOPC = 2'b01; SFTIN = 1'b0; #10;
        $display("%b  %b  %b   %b  |  %b  %b", IN, SCNT, SHIFTOPC, SFTIN, OUT, SFTOUT);

        IN = 16'b1000_0000_0000_0000; SCNT = 4'b0001; SHIFTOPC = 2'b10; SFTIN = 1'b0; #10;
        $display("%b  %b  %b   %b  |  %b  %b", IN, SCNT, SHIFTOPC, SFTIN, OUT, SFTOUT);

        IN = 16'b0111_1111_1111_1111; SCNT = 4'b0011; SHIFTOPC = 2'b10; SFTIN = 1'b0; #10;
        $display("%b  %b  %b   %b  |  %b  %b", IN, SCNT, SHIFTOPC, SFTIN, OUT, SFTOUT);

        IN = 16'b1010_1010_1010_1010; SCNT = 4'b0011; SHIFTOPC = 2'b11; SFTIN = 1'b1; #10;
        $display("%b  %b  %b   %b  |  %b  %b", IN, SCNT, SHIFTOPC, SFTIN, OUT, SFTOUT);

        IN = 16'b1010_1010_1010_1010; SCNT = 4'b0000; SHIFTOPC = 2'b11; SFTIN = 1'b1; #10;
        $display("%b  %b  %b   %b  |  %b  %b", IN, SCNT, SHIFTOPC, SFTIN, OUT, SFTOUT);

        $finish;
    end

endmodule

shift/dump_shift.vcd
$date
	Tue Aug 11 15:52:48 2026
$end
$version
	Icarus Verilog
$end
$timescale
	1ps
$end
$scope module shift_tb $end
$var wire 16 ! OUT [15:0] $end
$var wire 1 " SFTOUT $end
$var reg 16 # IN [15:0] $end
$var reg 4 $ SCNT [3:0] $end
$var reg 1 % SFTIN $end
$var reg 2 & SHIFTOPC [1:0] $end
$scope module uut $end
$var wire 16 ' IN [15:0] $end
$var wire 16 ( OUT [15:0] $end
$var wire 4 ) SCNT [3:0] $end
$var wire 1 * SFTIN $end
$var wire 1 " SFTOUT $end
$var wire 2 + SHIFTOPC [1:0] $end
$var wire 4 , effSCNT [3:0] $end
$var wire 16 - out1 [15:0] $end
$var wire 16 . out2 [15:0] $end
$var wire 16 / out4 [15:0] $end
$var wire 1 0 sf1 $end
$var wire 1 1 sf2 $end
$var wire 1 2 sf4 $end
$scope module SHIFT1 $end
$var wire 1 3 EN $end
$var wire 16 4 IN [15:0] $end
$var wire 16 5 OUT [15:0] $end
$var wire 1 * SFTIN $end
$var wire 1 6 SFTOUT1 $end
$var wire 1 0 SFTOUT2 $end
$var wire 2 7 SHIFTOPC [1:0] $end
$var wire 1 8 fallenBit $end
$var wire 1 9 fillBit $end
$var wire 16 : leftShifted [15:0] $end
$var wire 16 ; rightShifted [15:0] $end
$var wire 16 < shiftedVal [15:0] $end
$upscope $end
$scope module SHIFT2 $end
$var wire 1 = EN $end
$var wire 16 > IN [15:0] $end
$var wire 16 ? OUT [15:0] $end
$var wire 1 * SFTIN $end
$var wire 1 0 SFTOUT1 $end
$var wire 1 1 SFTOUT2 $end
$var wire 2 @ SHIFTOPC [1:0] $end
$var wire 1 A fallenBit $end
$var wire 1 B fillBit $end
$var wire 16 C leftShifted [15:0] $end
$var wire 16 D rightShifted [15:0] $end
$var wire 16 E shiftedVal [15:0] $end
$upscope $end
$scope module SHIFT4 $end
$var wire 1 F EN $end
$var wire 16 G IN [15:0] $end
$var wire 16 H OUT [15:0] $end
$var wire 1 * SFTIN $end
$var wire 1 1 SFTOUT1 $end
$var wire 1 2 SFTOUT2 $end
$var wire 2 I SHIFTOPC [1:0] $end
$var wire 1 J fallenBit $end
$var wire 1 K fillBit $end
$var wire 16 L leftShifted [15:0] $end
$var wire 16 M rightShifted [15:0] $end
$var wire 16 N shiftedVal [15:0] $end
$upscope $end
$scope module SHIFT8 $end
$var wire 1 O EN $end
$var wire 16 P IN [15:0] $end
$var wire 16 Q OUT [15:0] $end
$var wire 1 * SFTIN $end
$var wire 1 2 SFTOUT1 $end
$var wire 1 " SFTOUT2 $end
$var wire 2 R SHIFTOPC [1:0] $end
$var wire 1 S fallenBit $end
$var wire 1 T fillBit $end
$var wire 16 U leftShifted [15:0] $end
$var wire 16 V rightShifted [15:0] $end
$var wire 16 W shiftedVal [15:0] $end
$upscope $end
$upscope $end
$upscope $end
$enddefinitions $end
#0
$dumpvars
b101100000000 W
b0 V
b101100000000 U
0T
0S
b0 R
b1011 Q
b1011 P
0O
b10110000 N
b0 M
b10110000 L
0K
0J
b0 I
b1011 H
b1011 G
0F
b101100 E
b10 D
b101100 C
0B
0A
b0 @
b1011 ?
b1011 >
0=
b10110 <
b101 ;
b10110 :
09
08
b0 7
06
b1011 5
b1011 4
03
02
01
00
b1011 /
b1011 .
b1011 -
b0 ,
b0 +
0*
b0 )
b1011 (
b1011 '
b0 &
0%
b0 $
b1011 #
0"
b1011 !
$end
#10000
b10110000000000 W
b1011000000 N
b10110000000000 U
b101100 !
b101100 (
b101100 Q
b1011000000 L
b10 M
b101100 /
b101100 H
b101100 P
b101100 .
b101100 ?
b101100 G
1=
b10 ,
b10 $
b10 )
#20000
1"
b1111111100000000 W
1S
b1111111111110000 N
1J
b1111111100000000 U
b11111111 V
b1111111111110000 L
b111111111111 M
b1111111111111111 /
b1111111111111111 H
b1111111111111111 P
b1111111111111111 .
b1111111111111111 ?
b1111111111111111 G
b1111111100000000 !
b1111111100000000 (
b1111111100000000 Q
b1111111111111100 E
1A
0=
1O
b1111111111111110 <
18
b1111111111111100 C
b11111111111111 D
b1000 ,
b1111111111111110 :
b111111111111111 ;
b1111111111111111 -
b1111111111111111 5
b1111111111111111 >
b1000 $
b1000 )
b1111111111111111 #
b1111111111111111 '
b1111111111111111 4
#30000
0S
0J
b0 U
b1000000 V
0"
0A
b0 L
b10000000000 M
b100000000000000 /
b100000000000000 H
b100000000000000 P
b100000000000000 !
b100000000000000 (
b100000000000000 Q
13
0O
b0 C
b1000000000000 D
b100000000000000 .
b100000000000000 ?
b100000000000000 G
b100000000000000 <
08
b1000000000000 E
b10000000000 N
b1000000 W
b1 ,
b0 :
b100000000000000 ;
b100000000000000 -
b100000000000000 5
b100000000000000 >
b1 &
b1 +
b1 7
b1 @
b1 I
b1 R
b1 $
b1 )
b1000000000000000 #
b1000000000000000 '
b1000000000000000 4
#40000
1S
b1111111100000000 U
1"
12
b111111111111 N
1J
b1111 W
b11111111111111 E
1A
b1111111111110000 L
b111111111111 M
b1111 V
b111111111111 !
b111111111111 (
b111111111111 Q
b1111111111111100 C
b11111111111111 D
b1111111111111111 .
b1111111111111111 ?
b1111111111111111 G
b111111111111 /
b111111111111 H
b111111111111 P
b1111111111111111 -
b1111111111111111 5
b1111111111111111 >
03
1F
b111111111111111 <
18
b100 ,
b1111111111111110 :
b111111111111111 ;
b100 $
b100 )
b1111111111111111 #
b1111111111111111 '
b1111111111111111 4
#50000
1T
b1111111111000000 W
0S
b0 U
b1111111111000000 V
b1100000000000000 !
b1100000000000000 (
b1100000000000000 Q
0"
0J
b1100000000000000 /
b1100000000000000 H
b1100000000000000 P
02
0A
b0 L
b1111000000000000 E
b1111110000000000 N
13
0F
b1100000000000000 <
08
b0 C
b1100000000000000 .
b1100000000000000 ?
b1100000000000000 G
19
b1111000000000000 D
1B
b1111110000000000 M
1K
b1 ,
b0 :
b1100000000000000 ;
b1100000000000000 -
b1100000000000000 5
b1100000000000000 >
b10 &
b10 +
b10 7
b10 @
b10 I
b10 R
b1 $
b1 )
b1000000000000000 #
b1000000000000000 '
b1000000000000000 4
#60000
0T
0K
1S
1J
b1111111100000000 U
1"
b1111111111110000 L
12
b1111 W
0B
11
b11111111 N
b1111 V
b111111111111 !
b111111111111 (
b111111111111 Q
b111111111111 E
1A
b11111111 M
b111111111111 /
b111111111111 H
b111111111111 P
b1111111111111100 C
b111111111111 D
b111111111111 .
b111111111111 ?
b111111111111 G
b11111111111111 -
b11111111111111 5
b11111111111111 >
10
1=
09
b11111111111111 <
18
b11 ,
b1111111111111110 :
b11111111111111 ;
b11 $
b11 )
b111111111111111 #
b111111111111111 '
b111111111111111 4
#70000
0S
0"
0J
b101010100000000 U
b1101010101010101 !
b1101010101010101 (
b1101010101010101 Q
0A
02
b101010101010000 L
b1101010101010101 /
b1101010101010101 H
b1101010101010101 P
b101010101010100 C
01
b1101010101010101 .
b1101010101010101 ?
b1101010101010101 G
b1101010101010101 -
b1101010101010101 5
b1101010101010101 >
00
0=
b1111010101010101 E
b1111110101010101 N
b1111111111010101 W
b1101010101010101 <
08
b1 ,
19
b1111010101010101 D
1B
b1111110101010101 M
1K
b1111111111010101 V
1T
b101010101010100 :
b1101010101010101 ;
1%
1*
b11 &
b11 +
b11 7
b11 @
b11 I
b11 R
b1010101010101010 #
b1010101010101010 '
b1010101010101010 4
#80000
b0 $
b0 )
