shift/shift.v
//ShiftOPC == LSL, LSR, ASR, XSR
//LSL = <<
//LSR = >>
//ASR = >>>
//XSR = hardcode

module LSL(input signed [7:0] A, input [3:0] shiftVal, output [7:0] A_mod, output flagC);
    assign A_mod = A << shiftVal;
    assign flagC = (shiftVal == 0) ? 1'b0 : A[8 - shiftVal];
endmodule

module LSR(input signed [7:0] A, input [3:0] shiftVal, output [7:0] A_mod, output flagC);
    assign A_mod = A >> shiftVal;
    assign flagC = (shiftVal == 0) ? 1'b0 : A[shiftVal - 1];
endmodule

module ASR(input signed[7:0] A, input [3:0] shiftVal, output [7:0] A_mod, output flagC);
    assign A_mod = A >>> shiftVal;
    assign flagC = (shiftVal == 0) ? 1'b0 : A[shiftVal - 1];
endmodule

module mux4to1Bus(input [7:0] B, input [7:0] C, input [7:0] D, input [1:0] select, output reg [7:0] outputData);
    always @(select, B, C,D) begin
        case(select)
            2'b00: outputData = B;
            2'b01: outputData = C;
            2'b10: outputData = D;
            2'b11: outputData = 8'b0000_0000;
        endcase
    end
endmodule

module mux4to1Wire(input flagC1, input flagC2, input flagC3, input [1:0] select, output reg flagCNew);
    always @(select, flagC1, flagC2, flagC3) begin
        case(select)
            2'b00: flagCNew = flagC1;
            2'b01: flagCNew = flagC2;
            2'b10: flagCNew = flagC3;
            2'b11: flagCNew = 1'b0;
        endcase
    end
endmodule


module shift(input [7:0] A, input [3:0] shiftVal, input [1:0] shiftOPC, input flagC, output [7:0] A_mod, output flagCNew);
    wire [7:0] B,C,D;
    wire flagC1, flagC2, flagC3;
    LSL myLSL(.A(A), .shiftVal(shiftVal), .A_mod(B), .flagC(flagC1));
    LSR myLSR(.A(A), .shiftVal(shiftVal), .A_mod(C), .flagC(flagC2));
    ASR myASR(.A(A), .shiftVal(shiftVal), .A_mod(D), .flagC(flagC3));

    mux4to1Bus setOutput(.B(B), .C(C), .D(D), .select(shiftOPC), .outputData(A_mod));
    mux4to1Wire setFlag(.flagC1(flagC1), .flagC2(flagC2), .flagC3(flagC3),.select(shiftOPC), .flagCNew(flagCNew));
endmodule

shift/shift_tb.v
`timescale 1ns/1ps

module shift_tb;
    reg  [7:0] A;
    reg  [3:0] shiftVal;
    reg  [1:0] shiftOPC;
    reg        flagC;
    wire [7:0] A_mod;
    wire       flagCNew;

    shift uut (
        .A(A),
        .shiftVal(shiftVal),
        .shiftOPC(shiftOPC),
        .flagC(flagC),
        .A_mod(A_mod),
        .flagCNew(flagCNew)
    );

    initial begin
        $dumpfile("dump_shift.vcd");
        $dumpvars(0, shift_tb);

        $display("      A     SHIFTVAL OPC |    A_mod   flagCNew");
        $display("--------------------------------------------------");

        // LSL tests (OPC = 00)
        A = 8'b0000_1011; shiftVal = 4'b0000; shiftOPC = 2'b00; flagC = 1'b0; #10;
        $display("%b  %b     %b  |  %b     %b", A, shiftVal, shiftOPC, A_mod, flagCNew);

        A = 8'b0000_1011; shiftVal = 4'b0010; shiftOPC = 2'b00; flagC = 1'b0; #10;
        $display("%b  %b     %b  |  %b     %b", A, shiftVal, shiftOPC, A_mod, flagCNew);

        A = 8'b1111_1111; shiftVal = 4'b1000; shiftOPC = 2'b00; flagC = 1'b0; #10;
        $display("%b  %b     %b  |  %b     %b", A, shiftVal, shiftOPC, A_mod, flagCNew);

        // LSR tests (OPC = 01)
        A = 8'b1000_0000; shiftVal = 4'b0001; shiftOPC = 2'b01; flagC = 1'b0; #10;
        $display("%b  %b     %b  |  %b     %b", A, shiftVal, shiftOPC, A_mod, flagCNew);

        A = 8'b1111_1111; shiftVal = 4'b0100; shiftOPC = 2'b01; flagC = 1'b0; #10;
        $display("%b  %b     %b  |  %b     %b", A, shiftVal, shiftOPC, A_mod, flagCNew);

        // ASR tests (OPC = 10)
        A = 8'b1000_0000; shiftVal = 4'b0001; shiftOPC = 2'b10; flagC = 1'b0; #10;
        $display("%b  %b     %b  |  %b     %b", A, shiftVal, shiftOPC, A_mod, flagCNew);

        A = 8'b0111_1111; shiftVal = 4'b0011; shiftOPC = 2'b10; flagC = 1'b0; #10;
        $display("%b  %b     %b  |  %b     %b", A, shiftVal, shiftOPC, A_mod, flagCNew);

        // Unused/default case (OPC = 11)
        A = 8'b1010_1010; shiftVal = 4'b0011; shiftOPC = 2'b11; flagC = 1'b0; #10;
        $display("%b  %b     %b  |  %b     %b", A, shiftVal, shiftOPC, A_mod, flagCNew);

        $finish;
    end

endmodule

shift/dump_shift.vcd
$date
	Sun Aug  2 22:11:26 2026
$end
$version
	Icarus Verilog
$end
$timescale
	1ps
$end
$scope module shift_tb $end
$var wire 1 ! flagCNew $end
$var wire 8 " A_mod [7:0] $end
$var reg 8 # A [7:0] $end
$var reg 1 $ flagC $end
$var reg 2 % shiftOPC [1:0] $end
$var reg 4 & shiftVal [3:0] $end
$scope module uut $end
$var wire 8 ' A [7:0] $end
$var wire 1 $ flagC $end
$var wire 2 ( shiftOPC [1:0] $end
$var wire 4 ) shiftVal [3:0] $end
$var wire 1 ! flagCNew $end
$var wire 1 * flagC3 $end
$var wire 1 + flagC2 $end
$var wire 1 , flagC1 $end
$var wire 8 - D [7:0] $end
$var wire 8 . C [7:0] $end
$var wire 8 / B [7:0] $end
$var wire 8 0 A_mod [7:0] $end
$scope module myASR $end
$var wire 8 1 A [7:0] $end
$var wire 4 2 shiftVal [3:0] $end
$var wire 1 * flagC $end
$var wire 8 3 A_mod [7:0] $end
$upscope $end
$scope module myLSL $end
$var wire 8 4 A [7:0] $end
$var wire 4 5 shiftVal [3:0] $end
$var wire 1 , flagC $end
$var wire 8 6 A_mod [7:0] $end
$upscope $end
$scope module myLSR $end
$var wire 8 7 A [7:0] $end
$var wire 4 8 shiftVal [3:0] $end
$var wire 1 + flagC $end
$var wire 8 9 A_mod [7:0] $end
$upscope $end
$scope module setFlag $end
$var wire 1 , flagC1 $end
$var wire 1 + flagC2 $end
$var wire 1 * flagC3 $end
$var wire 2 : select [1:0] $end
$var reg 1 ! flagCNew $end
$upscope $end
$scope module setOutput $end
$var wire 8 ; B [7:0] $end
$var wire 8 < C [7:0] $end
$var wire 8 = D [7:0] $end
$var wire 2 > select [1:0] $end
$var reg 8 ? outputData [7:0] $end
$upscope $end
$upscope $end
$upscope $end
$enddefinitions $end
$comment Show the parameter values. $end
$dumpall
$end
#0
$dumpvars
b1011 ?
b0 >
b1011 =
b1011 <
b1011 ;
b0 :
b1011 9
b0 8
b1011 7
b1011 6
b0 5
b1011 4
b1011 3
b0 2
b1011 1
b1011 0
b1011 /
b1011 .
b1011 -
0,
0+
0*
b0 )
b0 (
b1011 '
b0 &
b0 %
0$
b1011 #
b1011 "
0!
$end
#10000
1*
b101100 "
b101100 0
b101100 ?
1+
b10 -
b10 3
b10 =
b101100 /
b101100 6
b101100 ;
b10 .
b10 9
b10 <
b10 &
b10 )
b10 2
b10 5
b10 8
#20000
1!
1,
b0 "
b0 0
b0 ?
b1000 &
b1000 )
b1000 2
b1000 5
b1000 8
b11111111 -
b11111111 3
b11111111 =
b0 /
b0 6
b0 ;
b0 .
b0 9
b0 <
b11111111 #
b11111111 '
b11111111 1
b11111111 4
b11111111 7
#30000
0!
0*
b1000000 "
b1000000 0
b1000000 ?
0+
b1 %
b1 (
b1 :
b1 >
b11000000 -
b11000000 3
b11000000 =
b1000000 .
b1000000 9
b1000000 <
b1 &
b1 )
b1 2
b1 5
b1 8
b10000000 #
b10000000 '
b10000000 1
b10000000 4
b10000000 7
#40000
1!
1*
b1111 "
b1111 0
b1111 ?
1+
b100 &
b100 )
b100 2
b100 5
b100 8
b11111111 -
b11111111 3
b11111111 =
b11110000 /
b11110000 6
b11110000 ;
b1111 .
b1111 9
b1111 <
b11111111 #
b11111111 '
b11111111 1
b11111111 4
b11111111 7
#50000
0!
0*
b11000000 "
b11000000 0
b11000000 ?
0+
b10 %
b10 (
b10 :
b10 >
b1 &
b1 )
b1 2
b1 5
b1 8
b11000000 -
b11000000 3
b11000000 =
b0 /
b0 6
b0 ;
b1000000 .
b1000000 9
b1000000 <
b10000000 #
b10000000 '
b10000000 1
b10000000 4
b10000000 7
#60000
1!
1*
b1111 "
b1111 0
b1111 ?
1+
b11 &
b11 )
b11 2
b11 5
b11 8
b1111 -
b1111 3
b1111 =
b11111000 /
b11111000 6
b11111000 ;
b1111 .
b1111 9
b1111 <
b1111111 #
b1111111 '
b1111111 1
b1111111 4
b1111111 7
#70000
0!
0*
b0 "
b0 0
b0 ?
0+
b11 %
b11 (
b11 :
b11 >
b11110101 -
b11110101 3
b11110101 =
b1010000 /
b1010000 6
b1010000 ;
b10101 .
b10101 9
b10101 <
b10101010 #
b10101010 '
b10101010 1
b10101010 4
b10101010 7
